README.md
setup.cfg
setup.py
decode/__init__.py
decode/job/__init__.py
decode/job/base.py
decode/job/imports.py
decode/job/run.py
decode/job/storage/__init__.py
decode/job/storage/factory.py
decode/job/storage/storage.py
decode/job/storage/backends/__init__.py
decode/job/storage/backends/filesystem.py
decode/job/storage/backends/s3.py
decode_job.egg-info/PKG-INFO
decode_job.egg-info/SOURCES.txt
decode_job.egg-info/dependency_links.txt
decode_job.egg-info/not-zip-safe
decode_job.egg-info/requires.txt
decode_job.egg-info/top_level.txt